{
  "level": "A2",
  "topic": "Shopping, prices, sizes, customer service",
  "day": "Day 20260629",
  "lesson_id": "LSN-20260629-A2-SHOPPING",
  "practice_markdown": "## Reading Source Verification\n| Source title | Publisher/Organization | Date/Access date | Final verified URL | URL status | Source type | Reliability check | How the passage uses the source |\n| --- | --- | --- | --- | --- | --- | --- | --- |\n| Fewer Products to Choose from Can Lead to Better Sales | VOA Learning English | February 14, 2024 / June 29, 2026 | https://learningenglish.voanews.com/a/fewer-products-to-choose-from-can-lead-to-better-sales/7480572.html | Active | Educational News Article | High - official VOA report | Adapted excerpt on choice overload & business retail strategies |\n\n## Warm-up\nAnswer the following questions in Vietnamese or English:\n1. Bạn có thích mua sắm trực tuyến không? Tại sao? (Do you like online shopping? Why?)\n2. Khi mua sắm, bạn thích một cửa hàng có quá nhiều sự lựa chọn hay chỉ có vài mặt hàng tốt nhất? (When shopping, do you prefer a store with too many choices or just a few of the best items?)\n3. Tại sao việc có quá nhiều sự lựa chọn đôi khi lại làm bạn cảm thấy mệt mỏi hoặc khó đưa ra quyết định? (Why does having too many options sometimes make you feel tired or hard to make a decision?)\n\n## Reading Passage\n### Fewer Products to Choose from Can Lead to Better Sales\n\nHistorically, businesses believed that offering a wide **variety** of **products** would attract more **customers**. However, recent studies show that having too many **choices** can **overwhelm** shoppers. When faced with 30 options of a single item, people feel overwhelmed and spend a lot of time. This makes shopping very **time-consuming**. Sometimes, they leave the store without making a **purchase** because they feel shopping is too **expensive** [R].\n\nTo **simplify** the **decision** process, many modern **businesses** are starting to **limit** their **options**. For example, Coca-Cola decided to **discontinue** about half of its drinks. An **automaker** like General Motors also reduced the **complexity** of its car options to lower manufacturing costs.\n\nExperts call this issue choice **overload**. When companies **reduce** the number of **options**, sales **volume** actually increases. For shoppers who practice **budgeting** [R], a smaller selection helps them make faster choices because they know exactly what they can **afford** [R]. This **strategic** change is a win-win for both stores and shoppers.\n\n## Questions for Reading\n### Questions 1–5: Do the following statements agree with the information given in the Reading Passage? Write:\n- **TRUE** if the statement agrees with the information\n- **FALSE** if the statement contradicts the information\n- **NOT GIVEN** if there is no information on this\n\n1. In the past, companies thought that having more products would attract more customers.\n2. Shoppers are more likely to buy an item when they have 30 different options to choose from.\n3. Coca-Cola stopped selling all of its drinks to save money.\n4. General Motors reduced option combinations to lower their production costs.\n5. Reducing options makes shopping harder for people who plan their spending. (*)\n\n### Questions 6–9: Answer the questions below. Choose NO MORE THAN THREE WORDS or A NUMBER from the passage for each answer.\n6. What do customers experience when they are faced with too many choices?\n7. How many of its drink offerings did Coca-Cola decide to discontinue?\n8. What name do experts give to the problem of having too many choices?\n9. Beside stores, who else benefits from the strategic reduction of options? (*)\n\n### Questions 10–13: Choose the correct letter, A, B, or C.\n10. Why do some shoppers leave a store without buying anything?\n    - A. The products are too expensive.\n    - B. They feel overwhelmed by too many choices.\n    - C. The store does not have any discounts.\n11. Which company reduced car options to lower manufacturing costs?\n    - A. Coca-Cola\n    - B. General Motors\n    - C. Ford\n12. What does the word \"discontinue\" in the second paragraph most likely mean? (*)\n    - A. To stop making or selling a product.\n    - B. To increase the price of a product.\n    - C. To advertise a product more.\n13. What is the main idea of the passage? (*)\n    - A. Online shopping is better than traditional shopping.\n    - B. Companies are reducing choices to simplify shopping and increase sales.\n    - C. Shoppers should spend more money on cars.\n\n## Questions for Grammar\n### Choose the correct letter, A, B, or C.\n1. There ______ many products on this shelf.\n    - A. is\n    - B. are\n    - C. am\n2. I do not have ______ money to buy a new phone.\n    - A. many\n    - B. much\n    - C. some\n3. Would you like ______ tea while you wait?\n    - A. any\n    - B. some\n    - C. many\n4. The red shirt is significantly ______ than the blue one.\n    - A. cheap\n    - B. cheaper\n    - C. cheapest\n5. Shoppers ______ compare prices before making a purchase.\n    - A. should\n    - B. must to\n    - C. could\n6. Look! That store ______ a big discount today.\n    - A. offers\n    - B. is offering\n    - C. offered\n7. I only bought ______ apples because they were expensive.\n    - A. a few\n    - B. a little\n    - C. much\n8. The shop assistant ______ helped me was very kind. (*)\n    - A. who\n    - B. which\n    - C. whose\n9. Shop A is very crowded, ______ Shop B is quiet. (*)\n    - A. because\n    - B. whereas\n    - C. so\n10. If I have enough money, I ______ buy that jacket. (*)\n    - A. would\n    - B. will\n    - C. did\n\n### Fill in the blanks with the correct word in brackets.\n11. There ______ (is / are) some fruit in the shopping basket.\n12. We ______ (went / go) to the supermarket yesterday evening.\n13. He ______ (does not buy / not buys) any expensive clothes.\n14. They ______ (have lived / lived) in this city since last year.\n15. How ______ (many / much) options do we have?\n16. The price of this bag is twice as ______ (expensive / more expensive) as that one.\n17. You ______ (should / must) not take photos in this store. It is against the rules.\n18. This is the mall ______ (where / which) I bought my shoes. (*)\n19. If Shop A were cheaper, I ______ (will / would) buy my clothes there. (*)\n20. She ______ (has already chosen / already chose) a gift for her mother. (*)\n\n### Rewrite the sentences or correct the errors.\n21. Correct the error: The price in Shop A is significantly cheap than in Shop B.\n22. Correct the error: There is many customers waiting in line.\n23. Correct the error: I don't need some help from the assistant.\n24. Correct the error: This shirt is twice cheaper than that one.\n25. Correct the error: This bag is slightly expensive than that one.\n26. Correct the error: You must to show your receipt at the exit.\n27. Correct the error: My friend who works at the store gave me a discount. (*)\n28. Correct the error: Online shopping is easy. Traditional shopping, whereas, offers a tactile experience. (*)\n29. Correct the error: I shop at this supermarket since 2021. (*)\n30. Combine the sentences using a relative clause: This is the laptop. I purchased it yesterday. (*)\n\n## Questions for Writing\n| # | Task | Target length | Focus skill | Useful language | Success criteria |\n| --- | --- | --- | --- | --- | --- |\n| 1 | Word Ordering: Sắp xếp từ thành câu.<br>a) buy / clothes / online / I / .<br>b) store / many / has / products / the / . | Complete sentences | Word order in simple sentences | S + V + O | Correct capitalization and punctuation |\n| 2 | Sentence Completion: Điền thông tin.<br>a) I like this shop because it is ______ .<br>b) Yesterday, I bought a ______ . | 2 short clauses | Clause coordination with because/and | because, yesterday | Subject-verb agreement |\n| 3 | Translation: Dịch câu sang tiếng Anh.<br>a) Cửa hàng này có giá cả phải chăng.<br>b) Tôi muốn mua một sản phẩm mới. | 2 sentences | Simple description structure | affordable, want to buy | Correct vocabulary and be verbs |\n| 4 | Visual Data Description: Viết 3 câu đơn giản.<br>Describe the data shown in the chart below comparing the number of products in Shop A and Shop B.<br><br><div class=\"svg-chart-container\"><svg viewBox=\"0 0 400 200\" width=\"100%\" height=\"200\" style=\"background-color: #f8f9fa; border: 1px solid #dee2e6; border-radius: 4px;\"><line x1=\"50\" y1=\"150\" x2=\"350\" y2=\"150\" stroke=\"#ccc\" stroke-width=\"1\" /><line x1=\"50\" y1=\"100\" x2=\"350\" y2=\"100\" stroke=\"#eee\" stroke-width=\"1\" /><line x1=\"50\" y1=\"50\" x2=\"350\" y2=\"50\" stroke=\"#eee\" stroke-width=\"1\" /><text x=\"35\" y=\"155\" font-family=\"Arial\" font-size=\"10\" fill=\"#666\">0</text><text x=\"30\" y=\"105\" font-family=\"Arial\" font-size=\"10\" fill=\"#666\">10</text><text x=\"30\" y=\"55\" font-family=\"Arial\" font-size=\"10\" fill=\"#666\">20</text><rect x=\"100\" y=\"100\" width=\"50\" height=\"50\" fill=\"#3498db\" rx=\"2\" /><text x=\"125\" y=\"90\" font-family=\"Arial\" font-size=\"11\" font-weight=\"bold\" fill=\"#333\" text-anchor=\"middle\">10</text><rect x=\"230\" y=\"50\" width=\"50\" height=\"100\" fill=\"#e74c3c\" rx=\"2\" /><text x=\"255\" y=\"40\" font-family=\"Arial\" font-size=\"11\" font-weight=\"bold\" fill=\"#333\" text-anchor=\"middle\">20</text><text x=\"125\" y=\"170\" font-family=\"Arial\" font-size=\"12\" font-weight=\"bold\" fill=\"#555\" text-anchor=\"middle\">Shop A</text><text x=\"255\" y=\"170\" font-family=\"Arial\" font-size=\"12\" font-weight=\"bold\" fill=\"#555\" text-anchor=\"middle\">Shop B</text></svg></div> | 20-30 words | Simple data comparison | Shop A has..., Shop B has..., twice as many | Clear comparison sentences using A2 modifiers |\n| 5 | Guided Email invitation (*): Viết email ngắn.<br>Invite a friend to go shopping with you at the new shopping mall this Sunday. Mention what time to meet. | 25-35 words | Basic informal letter structure | Would you like to..., Let's meet at... | Include greeting, invite, time, and closing |",
  "vocabulary_grammar_markdown": "## Vocabulary Table\n| Từ/Cụm từ | Phiên âm | Loại từ | Định nghĩa và Tiếng Việt | Ví dụ minh họa |\n| --- | --- | --- | --- | --- |\n| choice | /tʃɔɪs/ | noun | Sự lựa chọn (an act of choosing between options) | There is a wide **choice** of shoes in this store. |\n| product | /ˈprɒd.ʌkt/ | noun | Sản phẩm (something that is made to be sold) | This shop sells high-quality **products**. |\n| business | /ˈbɪz.nɪs/ | noun | Doanh nghiệp, việc kinh doanh (the activity of buying and selling) | Many small **businesses** closed during the pandemic. |\n| customer | /ˈkʌs.tə.mər/ | noun | Khách hàng (a person who buys goods or services) | The shop assistant is helping a **customer**. |\n| overwhelm | /ˌəʊ.vəˈwelm/ | verb | Làm quá tải, ngợp (to give someone too much of something) | Too many options can **overwhelm** the shoppers. |\n| necessity | /nəˈses.ə.ti/ | noun | Nhu yếu phẩm, sự cần thiết (something that you need) | Food and clothing are basic **necessities**. |\n| reduce | /rɪˈdʒuːs/ | verb | Giảm bớt (to make something smaller or less) | We need to **reduce** our monthly spending. |\n| purchase | /ˈpɜː.tʃəs/ | verb/noun | Mua / Món đồ mua (to buy something / the act of buying) | She decided to **purchase** a new dress. |\n| option | /ˈɒp.ʃən/ | noun | Tùy chọn, phương án (one of the choices you can make) | Students have the **option** to study online. |\n| discontinue | /ˌdɪs.kənˈtɪn.juː/ | verb | Ngừng cung cấp, ngừng bán (to stop making or selling) | The company will **discontinue** this model next year. |\n| automaker | /ˈɔː.təʊ.meɪ.kər/ | noun | Nhà sản xuất ô tô (a company that makes cars) | General Motors is a famous American **automaker**. |\n| limit | /ˈlɪm.ɪt/ | verb/noun | Giới hạn (to keep something below a certain point) | You should **limit** the amount of sugar you eat. |\n| complexity | /kəmˈplek.sɪ.ti/ | noun | Sự phức tạp (the state of having many different parts) | The **complexity** of the menu makes it hard to choose. |\n| strategic | /strəˈtiː.dʒɪk/ | adjective | Mang tính chiến lược (helping to achieve a plan) | Reducing options was a **strategic** business decision. |\n| volume | /ˈvɒl.juːm/ | noun | Sản lượng, số lượng (the amount of something) | The store wants to increase its sales **volume**. |\n| variety | /vəˈraɪ.ə.ti/ | noun | Sự đa dạng (a number of different types of things) | The supermarket offers a wide **variety** of vegetables. |\n| overload | /ˌəʊ.vəˈlhəʊd/ | noun | Sự quá tải (too much of something) | Having 50 choices causes choice **overload**. |\n| simplify | /ˈsɪm.plɪ.faɪ/ | verb | Đơn giản hóa (to make something easier to understand) | The new app will **simplify** online payment. |\n| time-consuming | /ˈtaɪm.kənˌsjuː.mɪŋ/ | adjective | Tốn thời gian (taking a lot of time) | Shopping in crowded malls is very **time-consuming**. |\n| decision | /dɪˈsɪʒ.ən/ | noun | Quyết định (a choice that you make after thinking) | Buying a house is an important **decision**. |\n\n## Recycled Vocabulary (Từ vựng ôn tập)\n| Từ/Cụm từ | Phiên âm | Loại từ | Định nghĩa và Tiếng Việt | Bài học gốc (Day) |\n| --- | --- | --- | --- | --- |\n| afford | /əˈfɔːd/ | verb | Có đủ khả năng chi trả | Day 20260628 |\n| budgeting | /ˈbʌdʒɪtɪŋ/ | noun | Việc lập ngân sách | Day 20260628 |\n| expensive | /ɪkˈspensɪv/ | adjective | Đắt đỏ, tốn kém | Day 20260628 |\n\n## Vocabulary Grouping Notes\n- **Academic Vocab**: product, necessity, reduce, complexity, strategic, volume, simplify, decision.\n- **Compound Words**: automaker, time-consuming, choice overload.\n- **Idioms & Phrases / Useful Chunks**: wide variety of, make a purchase, decide to, be overwhelmed by, spend time.\n\n## Detailed Grammar Guide\n#### Chủ điểm 1: Countable & Uncountable Nouns, Some/Any/Much/Many\n- **Danh từ đếm được (Countable Nouns)**: Có thể đếm bằng số, có dạng số nhiều (ví dụ: *product -> products, customer -> customers*). Đi với *many, a few, some, any*.\n- **Danh từ không đếm được (Uncountable Nouns)**: Không thể đếm trực tiếp, không có dạng số nhiều (ví dụ: *money, information, time, choice (khi nói chung về sự lựa chọn)*). Đi với *much, a little, some, any*.\n- **Some & Any**:\n  - *Some* dùng trong câu khẳng định hoặc lời mời lịch sự: \"I have **some** products.\" / \"Would you like **some** tea?\"\n  - *Any* dùng trong câu phủ định và câu hỏi: \"I don't have **any** cash.\" / \"Do you have **any** discount?\"\n- **Much & Many**:\n  - *Many* + danh từ đếm được số nhiều: \"How **many** products do you have?\"\n  - *Much* + danh từ không đếm được: \"How **much** money is this shirt?\"\n\n#### Chủ điểm 2: Basic Data Comparison Modifiers\n- Khi mô tả biểu đồ hoặc so sánh số liệu (nhất là trong IELTS Task 1), chúng ta sử dụng các từ bổ nghĩa để làm rõ mức độ khác biệt:\n  - **significantly / much** (nhiều, đáng kể): \"The price in Shop B is **significantly** higher than Shop A.\"\n  - **slightly / a little** (một chút, nhẹ): \"Shop B has **slightly** more customers than Shop A.\"\n  - **twice as ... as / half as ... as** (gấp đôi / bằng một nửa): \"Shop B has **twice as** many products **as** Shop A.\"\n\n#### Tips & Tricks: Tránh lỗi so sánh gấp nhiều lần (Ratio Trap)\n- Khi dùng so sánh bội số (gấp 2, 3 lần), cấu trúc đúng phải là `twice/three times + as + adj/many + as`. Tránh viết nhầm thành `twice higher than` hoặc `twice cheaper than`. Đúng: \"The price is **twice as high as** that one.\"\n\n## Common Mistakes / IELTS Traps for This Topic\n| Common mistake / Trap | Wrong example | Correct version | Why it matters for IELTS |\n| --- | --- | --- | --- |\n| Dùng \"many\" với danh từ không đếm được | There isn't **many** money left for shopping. | There isn't **much** money left for shopping. | Giảm điểm tiêu chí Grammatical Accuracy nếu sai danh từ đếm được/không đếm được. |\n| Lỗi so sánh bội số không chuẩn | Shop B is **twice cheaper than** Shop A. | Shop B is **half as expensive as** Shop A. | Sai ngữ pháp cơ bản khi viết câu so sánh trong Task 1. |\n| Thiếu \"as\" thứ hai trong so sánh bội số | Shop B has twice **as many products Shop A**. | Shop B has twice **as many products as** Shop A. | Cấu trúc so sánh bội số bắt buộc phải là \"twice as + adj/many + as\". |\n| Dùng \"some\" trong câu phủ định | I don't need **some** customer support. | I don't need **any** customer support. | Dùng sai mạo từ/từ chỉ định lượng làm câu mất tự nhiên. |\n| Sai giới từ với động từ \"spend\" | I spent $20 **for** this bag. | I spent $20 **on** this bag. | Sai cụm động từ (verb preposition collocation) làm mất điểm từ vựng. |",
  "answers_markdown": "## Reading Answer Key and Detailed Explanations\n\n📖 **Tóm tắt bài đọc:** Bài đọc nói về xu hướng giảm bớt sản phẩm của các doanh nghiệp để đơn giản hóa trải nghiệm mua sắm và tăng doanh số. Theo nghiên cứu, việc có quá nhiều sự lựa chọn (ví dụ 30 sự lựa chọn cho cùng một mặt hàng) sẽ làm khách hàng bị quá tải (overwhelm), cảm thấy bị ngợp và tốn thời gian, dẫn đến việc họ rời cửa hàng mà không mua gì vì họ cảm thấy việc mua sắm quá đắt đỏ và tốn thời gian. Do đó, các thương hiệu lớn như Coca-Cola hay hãng xe General Motors đều chủ động giới hạn các phương án lựa chọn nhằm tăng doanh số và giúp khách hàng dễ dàng đưa ra quyết định hơn.\n\n1. **TRUE** — In the past, companies thought that having more products would attract more customers.\n- Bằng chứng: \"Historically, businesses believed that offering a wide variety of products would attract more customers.\" (§1)\n- Cách tìm đáp án: Tìm từ khóa \"In the past\" tương ứng với \"Historically\" (Về mặt lịch sử / Trong quá khứ). Mệnh đề phía sau nói các doanh nghiệp tin tưởng việc đưa ra sự đa dạng sản phẩm sẽ thu hút nhiều khách hàng hơn, hoàn toàn khớp với câu hỏi → Chọn **TRUE**.\n> **💡 Mẹo:** \"Historically\" là một từ chỉ thời gian trong quá khứ, thường được paraphrase bằng \"In the past\" hoặc \"In the old days\" trong câu hỏi IELTS.\n\n2. **FALSE** — Shoppers are more likely to buy an item when they have 30 different options to choose from.\n- Bằng chứng: \"When faced with 30 options of a single item, people feel overwhelmed... Sometimes, they leave the store without making a purchase...\" (§1)\n- Cách tìm đáp án: Tìm từ khóa \"30 options\" ở đoạn 1. Bài viết chỉ ra khi đối mặt với 30 lựa chọn, người ta cảm thấy ngợp và đôi khi rời đi mà không mua gì (\"leave the store without making a purchase\"). Điều này mâu thuẫn với nhận định \"more likely to buy\" (dễ mua hơn) của câu hỏi → Chọn **FALSE**.\n> **💡 Mẹo:** Các từ chỉ tần suất hoặc khả năng xảy ra như \"more likely to\", \"less likely to\" thường là bẫy chính trong các câu True/False/Not Given. Cần kiểm tra kỹ xu hướng thực tế của thông tin.\n\n3. **FALSE** — Coca-Cola stopped selling all of its drinks to save money.\n- Bằng chứng: \"For example, Coca-Cola decided to discontinue about half of its drinks.\" (§2)\n- Cách tìm đáp án: Tìm từ khóa \"Coca-Cola\" ở đoạn 2. Bài viết viết hãng quyết định ngừng cung cấp khoảng một nửa số đồ uống của mình (\"discontinue about half of its drinks\"). Câu hỏi nói dừng bán \"all of its drinks\" (tất cả đồ uống) là sai lệch hoàn toàn với \"half\" → Chọn **FALSE**.\n> **💡 Mẹo:** \"All\" (tất cả) là từ khóa mang tính tuyệt đối, trong khi bài đọc chỉ ghi \"half\" (một nửa). Gặp các chi tiết số lượng đối lập như vậy thì câu trả lời chắc chắn là FALSE.\n\n4. **TRUE** — General Motors reduced option combinations to lower their production costs.\n- Bằng chứng: \"An automaker like General Motors also reduced the complexity of its car options to lower manufacturing costs.\" (§2)\n- Cách tìm đáp án: Tìm từ khóa \"General Motors\" ở đoạn 2. Bài viết viết GM đã giảm sự phức tạp của các tùy chọn xe (\"reduced the complexity of its car options\") nhằm giảm chi phí sản xuất (\"lower manufacturing costs\"). Cụm \"production costs\" đồng nghĩa với \"manufacturing costs\" → Chọn **TRUE**.\n> **💡 Mẹo:** Nhận diện cặp từ đồng nghĩa: \"production costs\" = \"manufacturing costs\".\n\n5. **FALSE** *[Stretch Point]* — Reducing options makes shopping harder for people who plan their spending.\n- Bằng chứng: \"For shoppers who practice budgeting [R], a smaller selection helps them make faster choices because they know exactly what they can afford [R].\" (§3)\n- Cách tìm đáp án: Đoạn 3 nói đối với người mua sắm thực hành lập ngân sách (budgeting), việc lựa chọn ít hơn giúp họ đưa ra quyết định nhanh hơn vì họ biết mình có khả năng chi trả những gì (\"helps them make faster choices because they know exactly what they can afford [R]\"). Như vậy việc giảm bớt lựa chọn làm việc mua sắm của họ dễ hơn và nhanh hơn, chứ không phải khó hơn (\"makes shopping harder\") → Chọn **FALSE**.\n> **💡 Mẹo:** \"plan their spending\" chính là cách paraphrase cụm từ \"practice budgeting\" trong bài viết. Cần liên kết từ vựng tương đương để suy luận đúng.\n\n6. **overwhelmed**\n- Bằng chứng: \"When faced with 30 options of a single item, people feel overwhelmed...\" (§1)\n- Cách tìm đáp án: Câu hỏi hỏi khách hàng trải nghiệm cảm xúc gì (\"What do customers experience...?\") khi có quá nhiều lựa chọn. Tìm trong đoạn 1 cụm \"feel\" đi kèm từ chỉ sự quá tải, ngợp → Điền **overwhelmed**.\n\n7. **about half**\n- Bằng chứng: \"...Coca-Cola decided to discontinue about half of its drinks.\" (§2)\n- Cách tìm đáp án: Tìm từ khóa \"Coca-Cola\" và \"discontinue\". Đoạn 2 chỉ ra số lượng đồ uống ngừng bán là \"about half\" → Điền **about half**.\n\n8. **choice overload**\n- Bằng chứng: \"Experts call this issue choice overload.\" (§3)\n- Cách tìm đáp án: Tìm từ khóa \"experts call\" và \"issue\". Đoạn 3 chỉ ra tên gọi của vấn đề này là \"choice overload\" → Điền **choice overload**.\n\n9. **shoppers** *[Stretch Point]*\n- Bằng chứng: \"This strategic change is a win-win for both stores and shoppers.\" (§3)\n- Cách tìm đáp án: Từ khóa \"win-win\" thể hiện mối quan hệ đôi bên cùng có lợi (cửa hàng và người mua). Ngoài \"stores\" đã nêu ở câu hỏi, đối tượng còn lại là \"shoppers\" → Điền **shoppers**.\n> **💡 Mẹo:** Cấu trúc \"both A and B\" trong bài viết tương đương với \"Beside A, who is B?\" trong câu hỏi.\n\n10. **B** — They feel overwhelmed by too many choices.\n- Cách tìm đáp án: Đọc đoạn 1 để tìm nguyên nhân rời đi không mua gì. Bài viết viết: \"too many choices can overwhelm shoppers... Sometimes, they leave the store without making a purchase.\" Ý này trùng khớp với phương án B. A và C không được nhắc tới. → Chọn **B**.\n\n11. **B** — General Motors\n- Cách tìm đáp án: Tìm từ khóa \"lower manufacturing costs\". Đoạn 2 viết rõ \"An automaker like General Motors also reduced... to lower manufacturing costs\" → Chọn **B**.\n\n12. **A** *[Stretch Point]* — To stop making or selling a product.\n- Cách tìm đáp án: Từ \"discontinue\" dùng trong bối cảnh Coca-Cola ngừng bán một nửa đồ uống của họ. Dựa trên hậu tố \"dis-\" (ngừng, không) và \"continue\" (tiếp tục), học viên trình độ B1 có thể đoán được nghĩa là ngừng sản xuất hoặc bán sản phẩm → Chọn **A**.\n\n13. **B** *[Stretch Point]* — To explain how reducing choices can help companies increase sales and simplify shopping.\n- Cách tìm đáp án: Toàn bộ bài đọc mô tả thực trạng quá tải lựa chọn và cách các công ty giải quyết bằng cách giảm bớt sản phẩm để tăng hiệu quả bán hàng. Phương án B thể hiện trọn vẹn ý chính này. A quá cụ thể và không phải trọng tâm chính, C không chính xác. → Chọn **B**.\n\n## Grammar Answer Key and Detailed Explanations\n\n> **Bảng phân biệt nhanh / Công thức bỏ túi:**\n> - **Danh từ đếm được số nhiều**: đi với *many, a few, any/some*. Ví dụ: *products, options*.\n> - **Danh từ không đếm được**: đi với *much, a little, any/some*. Ví dụ: *money, time*.\n> - **Comparative Modifiers**: *significantly/slightly + Adj-er + than*.\n> - **Ratio Comparison**: *twice as + adj/many + as* (gấp hai lần).\n\n1. **B. are**\n- Dấu hiệu / Phân tích: Chủ ngữ là danh từ số nhiều \"many products\" đứng sau cấu trúc \"There\" → động từ to be chia ở số nhiều ở hiện tại là **are**.\n> **💡 Mẹo:** Luôn nhìn danh từ đi sau \"There is/are\" để xác định dạng động từ.\n\n2. **B. much**\n- Dấu hiệu / Phân tích: Danh từ \"money\" (tiền) là danh từ không đếm được. Câu phủ định \"do not have\" → dùng **much** để nhấn mạnh lượng tiền ít.\n> **💡 Mẹo:** Hãy nhớ \"money\" là danh từ không đếm được, luôn đi với \"much\" hoặc \"a little\".\n\n3. **B. some**\n- Dấu hiệu / Phân tích: Đây là câu hỏi đề nghị / mời lịch sự (\"Would you like...?\") → dùng **some** thay vì \"any\".\n> **💡 Mẹo:** \"some\" có thể dùng trong câu hỏi mang tính chất mời mọc, đề nghị hoặc khi mong đợi câu trả lời \"yes\".\n\n4. **B. cheaper**\n- Dấu hiệu / Phân tích: Có từ \"than\" chỉ so sánh hơn. Trạng từ \"significantly\" bổ nghĩa làm rõ mức độ khác biệt → điền tính từ so sánh hơn là **cheaper**.\n\n5. **A. should**\n- Dấu hiệu / Phân tích: Diễn tả một lời khuyên hữu ích cho người mua sắm (\"Shoppers should compare...\") → chọn động từ khuyết thiếu **should**. B sai vì \"must\" không đi với \"to V\".\n\n6. **B. is offering**\n- Dấu hiệu / Phân tích: Từ hô cảm \"Look!\" (Nhìn kìa!) báo hiệu một hành động đang xảy ra trước mắt → dùng thì **Hiện tại tiếp diễn** (is offering).\n\n7. **A. a few**\n- Dấu hiệu / Phân tích: Danh từ \"apples\" là danh từ đếm được số nhiều. Mệnh đề kết quả \"because they were expensive\" cho thấy số lượng mua rất ít → dùng **a few**.\n> **💡 Mẹo:** a few + danh từ đếm được số nhiều | a little + danh từ không đếm được.\n\n8. **A. who** *[Stretch Point]*\n- Kỹ năng B1 — Đại từ quan hệ chỉ người: Mệnh đề quan hệ bổ nghĩa cho danh từ chỉ người \"The shop assistant\", làm chủ ngữ cho động từ \"helped\" → dùng **who**.\n\n9. **B. whereas** *[Stretch Point]*\n- Kỹ năng B1 — Từ nối tương phản mệnh đề: Nối hai mệnh đề chỉ trạng thái đối lập của hai cửa hàng trong cùng một câu → dùng liên từ **whereas** (trong khi đó).\n\n10. **B. will** *[Stretch Point]*\n- Kỹ năng B1 — Câu điều kiện loại 1: Mệnh đề điều kiện dùng hiện tại đơn (\"If I have...\"), mệnh đề chính chỉ kết quả có thể xảy ra ở tương lai → dùng **will** + V.\n\n11. **is**\n- Dấu hiệu / Phân tích: Danh từ \"fruit\" (trái cây nói chung) là danh từ không đếm được → động từ to be chia số ít đi sau \"There\" là **is**.\n\n12. **went**\n- Dấu hiệu / Phân tích: Trạng ngữ thời gian quá khứ xác định \"yesterday evening\" → động từ chia ở quá khứ đơn của \"go\" là **went**.\n\n13. **does not buy**\n- Dấu hiệu / Phân tích: Phủ định của động từ thường ở hiện tại đơn số ít với chủ ngữ \"He\" → dùng trợ động từ phủ định **does not buy**.\n\n14. **have lived**\n- Dấu hiệu / Phân tích: Dấu hiệu thời gian \"since last year\" chỉ hành động kéo dài từ quá khứ đến hiện tại → chia thì Hiện tại hoàn thành **have lived** với chủ ngữ \"They\".\n\n15. **many**\n- Dấu hiệu / Phân tích: Danh từ \"options\" (tùy chọn) là danh từ đếm được số nhiều → từ hỏi lượng đi kèm là **How many**.\n\n16. **expensive**\n- Dấu hiệu / Phân tích: Cấu trúc so sánh bội số \"twice as ... as\" đòi hỏi tính từ gốc nguyên mẫu ở giữa → điền **expensive** (không dùng so sánh hơn \"more expensive\").\n\n17. **must**\n- Dấu hiệu / Phân tích: Diễn tả một quy định cấm đoán nghiêm khắc (\"must not do something\") → điền **must** để đi với \"not\".\n\n18. **where** *[Stretch Point]*\n- Kỹ năng B1 — Trạng từ quan hệ nơi chốn: Bổ nghĩa cho địa điểm \"the mall\" và trong mệnh đề có đầy đủ chủ ngữ \"I\" và động từ \"bought\" → dùng trạng từ quan hệ chỉ nơi chốn **where**.\n\n19. **would** *[Stretch Point]*\n- Kỹ năng B1 — Câu điều kiện loại 2: Mệnh đề \"If Shop A were cheaper\" (If + S + V2/ed) diễn tả giả thiết không có thực ở hiện tại. Mệnh đề chính chỉ kết quả tưởng tượng phải chia ở dạng `would` + V nguyên mẫu → điền **would**.\n> **💡 Mẹo:** Cấu trúc điều kiện loại 2: If + S + V2/ed, S + would + V-inf.\n\n20. **has already chosen** *[Stretch Point]*\n- Kỹ năng B1 — Trạng từ already với Hiện tại hoàn thành: Diễn tả hành động đã hoàn thành tính đến hiện tại → chia Hiện tại hoàn thành **has already chosen** (chủ ngữ \"She\").\n\n21. **cheaper**\n- Dấu hiệu / Phân tích: Lỗi so sánh hơn của tính từ ngắn \"cheap\" → Sửa \"significantly cheap than\" thành **cheaper** vì có \"than\".\n\n22. **are**\n- Dấu hiệu / Phân tích: Danh từ số nhiều \"many customers\" đi sau cấu trúc \"There\" → Sửa động từ to be \"is\" thành **are**.\n\n23. **any**\n- Dấu hiệu / Phân tích: Câu phủ định \"don't need\" không đi với \"some\" → Sửa \"some\" thành **any**.\n\n24. **twice as expensive as**\n- Dấu hiệu / Phân tích: Lỗi so sánh bội số dùng sai cấu trúc \"twice cheaper than\" → Sửa thành cấu trúc so sánh bằng bội số **twice as expensive as** (gấp hai lần giá) hoặc **half as expensive as** (bằng một nửa giá).\n\n25. **more expensive**\n- Dấu hiệu / Phân tích: So sánh hơn có \"than\" → Sửa tính từ gốc \"expensive\" thành **more expensive** hoặc cấu trúc so sánh hơn đúng là **cheaper / more expensive**. Cụ thể câu này sửa \"slightly expensive than\" thành **slightly more expensive than**.\n\n26. **must show**\n- Dấu hiệu / Phân tích: Động từ khuyết thiếu \"must\" đi trực tiếp với động từ nguyên mẫu không \"to\" → Sửa \"must to show\" thành **must show**.\n\n27. **My friend, who works at the store, gave me a discount.** *[Stretch Point]*\n- Kỹ năng B1 — Dấu phẩy mệnh đề quan hệ không xác định: \"My friend\" là danh từ xác định cụ thể trong ngữ cảnh giao tiếp → Mệnh đề quan hệ đi sau bổ sung ý cần dùng dấu phẩy ngăn cách.\n\n28. **by contrast / in contrast** *[Stretch Point]*\n- Kỹ năng B1 — Trạng từ nối tương phản câu: \"whereas\" không thể đứng giữa câu độc lập thứ hai có dấu phẩy đi sau như trạng từ → Sửa thành **by contrast** hoặc **in contrast** để nối câu.\n\n29. **have shopped / have been shopping** *[Stretch Point]*\n- Kỹ năng B1 — Thì Hiện tại hoàn thành với since: Có \"since 2021\" diễn tả hành động kéo dài từ quá khứ đến hiện tại → Sửa \"shop\" thành **have shopped** hoặc **have been shopping**.\n\n30. **This is the laptop which / that I purchased yesterday.** *[Stretch Point]*\n- Kỹ năng B1 — Nối câu bằng đại từ quan hệ: Dùng đại từ quan hệ \"which\" hoặc \"that\" để thay thế cho tân ngữ \"it\" chỉ vật bổ nghĩa cho danh từ \"laptop\".\n\n## Writing Guidance / Suggested Answers\n\n#### Task 1: Word Ordering\n> **Suggested Model Answer:**\n> a) I buy clothes online.\n> b) The store has many products.\n\n- **Hướng dẫn viết từng câu / từng bước:**\n  - Câu a: Xác định chủ ngữ \"I\", động từ \"buy\", tân ngữ \"clothes\", trạng từ chỉ phương thức \"online\". Kết hợp: \"I buy clothes online.\"\n  - Câu b: Chủ ngữ \"The store\", động từ số ít \"has\", cụm tân ngữ \"many products\". Kết hợp: \"The store has many products.\"\n- *Tự kiểm tra:* Kiểm tra dấu chấm câu và viết hoa chữ cái đầu câu.\n\n#### Task 2: Sentence Completion\n> **Suggested Model Answer:**\n> a) I like this shop because it is **very clean and cheap**.\n> b) Yesterday, I bought a **beautiful blue jacket at the mall**.\n\n- **Hướng dẫn viết từng câu / từng bước:**\n  - Câu a: Mệnh đề chỉ nguyên nhân bắtv đầu bằng \"because it is\" + cụm tính từ miêu tả tích cực về cửa hàng (\"clean and cheap\").\n  - Câu b: Hành động trong quá khứ có \"Yesterday\" → \"I bought a\" + cụm danh từ làm tân ngữ (\"beautiful blue jacket\") + trạng ngữ địa điểm (\"at the mall\").\n- *Tự kiểm tra:* Kiểm tra động từ \"bought\" chia đúng thì quá khứ đơn.\n\n#### Task 3: Translation\n> **Suggested Model Answer:**\n> a) This store is affordable.\n> b) I want to buy a new product.\n\n- **Hướng dẫn viết từng câu / từng bước:**\n  - Câu a: Dịch tương ứng: \"Cửa hàng này\" = This store + \"có giá cả phải chăng\" = is affordable.\n  - Câu b: Dịch tương ứng: \"Tôi\" = I + \"muốn mua\" = want to buy + \"một sản phẩm mới\" = a new product.\n- *Tự kiểm tra:* Đảm bảo cụm \"want to\" đi với động từ nguyên mẫu \"buy\".\n\n#### Task 4: Visual Data Description\n> **Suggested Model Answer:**\n> The chart compares the number of products in Shop A and Shop B. Shop A has 10 products, while Shop B has 20 products. Therefore, Shop B has twice as many products as Shop A.\n\n- **Hướng dẫn viết từng câu / từng bước:**\n  - Câu 1 (Giới thiệu biểu đồ): Mô tả ngắn gọn chủ đề biểu đồ: \"The chart compares the number of products in Shop A and Shop B.\"\n  - Câu 2 (Nêu số liệu cụ thể): Sử dụng từ nối tương phản \"while\" để so sánh số lượng sản phẩm của hai cửa hàng: \"Shop A has 10 products, while Shop B has 20 products.\"\n  - Câu 3 (So sánh bội số): Dùng cấu trúc so sánh bội số \"twice as many as\" để nêu bật mối quan hệ gấp đôi: \"Therefore, Shop B has twice as many products as Shop A.\"\n- *Tự kiểm tra:* Kiểm tra số lượng từ (khoảng 25-30 từ), cấu trúc \"twice as many ... as\" đúng chính tả.\n\n#### Task 5 (*): Guided Email invitation\n> **Suggested Model Answer:**\n> Hi Nam,\n> Would you like to go shopping with me at the new shopping mall this Sunday? We can buy some clothes. Let's meet at the mall entrance at 9:00 AM.\n> Best,\n> Hoa\n\n- **Hướng dẫn viết từng câu / từng bước:**\n  - Bước 1 (Lời chào): Hi + tên bạn,\n  - Bước 2 (Lời mời đi mua sắm): \"Would you like to go shopping with me at the new shopping mall this Sunday?\"\n  - Bước 3 (Hoạt động): \"We can buy some clothes.\"\n  - Bước 4 (Thời gian và địa điểm hẹn): \"Let's meet at the mall entrance at 9:00 AM.\"\n  - Bước 5 (Ký tên): Best, + tên.\n- *Tự kiểm tra:* Kiểm tra xem email có đủ các thông tin hẹn (chủ nhật này, lúc 9:00 sáng tại lối vào trung tâm thương mại) và viết đúng giới từ \"at\" chỉ địa điểm và thời gian.\n\n## Review Bridge\n#### IV. Review Bridge / Ôn tập liên chủ đề\n1. Dịch câu sau sang tiếng Anh, sử dụng từ vựng ôn tập của chủ đề mua sắm/tiền bạc: \"Nó quá đắt đỏ và tôi không thể mua nổi.\"\n- **Đáp án:** It is too expensive [R] and I cannot afford [R] it.\n- **Giải thích:** Sử dụng từ vựng ôn tập của Day 20260628: `expensive` và `afford`.\n\n2. Điền từ thích hợp: \"For shoppers who practice ______ [R], a smaller selection helps them save money.\"\n- **Đáp án:** budgeting\n- **Giải thích:** Từ vựng ôn tập Day 20260628: `budgeting`.\n\n3. Điền lượng từ thích hợp: \"There is not ______ (much / many) time left before the store closes.\"\n- **Đáp án:** much\n- **Giải thích:** \"time\" là danh từ không đếm được nên dùng \"much\" trong câu phủ định.\n",
  "quizlet_markdown": "## Section 1: Simple Vocabulary List (Học từ vựng đơn giản)\n| Từ vựng tiếng Anh | Nghĩa tiếng Việt |\n| --- | --- |\n| choice | sự lựa chọn |\n| product | sản phẩm |\n| business | doanh nghiệp, việc kinh doanh |\n| customer | khách hàng |\n| overwhelm | làm quá tải, ngợp |\n| necessity | nhu yếu phẩm, sự cần thiết |\n| reduce | giảm bớt |\n| purchase | mua / món đồ mua |\n| option | tùy chọn, phương án |\n| discontinue | ngừng cung cấp, ngừng bán |\n| automaker | nhà sản xuất ô tô |\n| limit | giới hạn |\n| complexity | sự phức tạp |\n| strategic | mang tính chiến lược |\n| volume | sản lượng, số lượng |\n| variety | sự đa dạng |\n| overload | sự quá tải |\n| simplify | đơn giản hóa |\n| time-consuming | tốn thời gian |\n| decision | quyết định |\n\n## Section 2: Detailed Vocabulary List (Học từ vựng đầy đủ)\n| Từ vựng + IPA + Loại từ | Nghĩa tiếng Việt |\n| --- | --- |\n| choice /tʃɔɪs, n/ | sự lựa chọn |\n| product /ˈprɒd.ʌkt, n/ | sản phẩm |\n| business /ˈbɪz.nɪs, n/ | doanh nghiệp, việc kinh doanh |\n| customer /ˈkʌs.tə.mər, n/ | khách hàng |\n| overwhelm /ˌəʊ.vəˈwelm, v/ | làm quá tải, ngợp |\n| necessity /nəˈses.ə.ti, n/ | nhu yếu phẩm, sự cần thiết |\n| reduce /rɪˈdʒuːs, v/ | giảm bớt |\n| purchase /ˈpɜː.tʃəs, v/n/ | mua / món đồ mua |\n| option /ˈɒp.ʃən, n/ | tùy chọn, phương án |\n| discontinue /ˌdɪs.kənˈtɪn.juː, v/ | ngừng cung cấp, ngừng bán |\n| automaker /ˈɔː.təʊ.meɪ.kər, n/ | nhà sản xuất ô tô |\n| limit /ˈlɪm.ɪt, v/n/ | giới hạn |\n| complexity /kəmˈplek.sɪ.ti, n/ | sự phức tạp |\n| strategic /strəˈtiː.dʒɪk, adj/ | mang tính chiến lược |\n| volume /ˈvɒl.juːm, n/ | sản lượng, số lượng |\n| variety /vəˈraɪ.ə.ti, n/ | sự đa dạng |\n| overload /ˌəʊ.vəˈlhəʊd, n/ | sự quá tải |\n| simplify /sɪm.plɪ.faɪ, v/ | đơn giản hóa |\n| time-consuming /taɪm.kən.sjuː.mɪŋ, adj/ | tốn thời gian |\n| decision /dɪˈsɪʒ.ən, n/ | quyết định |"
}